{"pageProps":{"post":{"id":"51","date":"2008. 4. 11. 21:33","title":"Ubuntu Live Conference 소식","content":"<div style=\"text-align: center;\"><a href=\"\" title=\"Ubuntu Live Homepage\"><img src=\"http://en.oreilly.com/ubuntu2008/public/asset/asset/532\" title=\"Ubuntu Live Logo\" style=\"border: 0px none ;\"></a></div>\n<br><a href=\"http://en.oreilly.com/ubuntu2008/public/content/home\" target=\"_blank\">Ubuntu Live Conference</a> 가 개최됩니다.<br><br><span style=\"font-weight: bold;\">When?</span> July 21-28, 2008<br><span style=\"font-weight: bold;\">Where?</span> <span lang=\"EN-US\">Portland, Oregon<br><br>회사에서 지원까지 해주는 듯하여 Ubuntu를 너무나 사랑하는 저로써는 정말 가고 싶지만 영어를 하나도 할 줄 모르는 상황에서 덜컥 신청할 수가 없네요.<br>누군가가 다녀오시고 소감문을 써주길 바랄 뿐입니다.<br><br><br><br><br></span>            ","summary":"\nUbuntu Live Conference 가 개최됩니다.When? July 21-28, 2008Where? Portland, Oregon회사에서 지원까지 해주는 듯하여 Ubuntu를 너무나 사랑하는 저로써는 정말 가고 싶지만 영어를 하나도 할 줄 모르는 상황에서 덜컥 신청할 수가 없네요.누군가가 다녀오시고 소감문을 써주길 바랄 뿐입니다.            ","image":"https://t1.daumcdn.net/tistory_admin/static/images/openGraph/opengraph.png"}},"__N_SSG":true}